agi_gui/AGILAB.py
agi_gui/__init__.py
agi_gui/agi_copilot.py
agi_gui/lab_run.py
agi_gui/pagelib.py
agi_gui/pages/▶️ EDIT.py
agi_gui/pages/▶️ EXECUTE.py
agi_gui/pages/▶️ EXPERIMENT.py
agi_gui/pages/▶️ VIEW.py
agi_gui/resources/__init__.py
agi_gui/resources/.agi/__init__.py
agi_gui/resources/.agi/agi_logo.png
agi_gui/resources/.agi/agilab_logo.png
agi_gui/resources/.agi/code_editor.scss
agi_gui/resources/.agi/custom_buttons.json
agi_gui/resources/.agi/info_bar.json
agi_gui/resources/.agi/help/__init__.py
agi_gui/resources/.agi/help/cluster-help.html
agi_gui/resources/.agi/help/edit_help.html
agi_gui/resources/.agi/help/execute_help.html
agi_gui/resources/.agi/help/experiment_help.html
agi_gui/resources/.agi/help/views_help.html
agi_gui-0.3.59.dist-info/licenses/LICENSE
agi_gui-0.3.59.dist-info/METADATA
agi_gui-0.3.59.dist-info/WHEEL
agi_gui-0.3.59.dist-info/entry_points.txt
agi_gui-0.3.59.dist-info/top_level.txt
agi_gui-0.3.59.dist-info/RECORD
