Metadata-Version: 2.4
Name: agi-gui
Version: 0.3.59
Summary: AGI GUI
Author-email: Jean-Pierre Morard <focus@thalesgroup.com>
Project-URL: Documentation, https://thalesgroup.github.io/agilab
Project-URL: Source, https://github.com/ThalesGroup/agilab/tree/main/src/agilab/fwk/gui
Project-URL: Tracker, https://github.com/ThalesGroup/agilab/issue
Keywords: jupyter,mlflow,asyncio,dask,rapids,streamlit,distributed,cython,cluster,dataframe,dataset,loadbalancing,genai,copilot,agi,pycharm,datascience
Classifier: Intended Audience :: Developers
Classifier: Development Status :: 3 - Alpha
Classifier: Programming Language :: Python :: 3
Classifier: Programming Language :: Python :: 3.11
Classifier: Programming Language :: Python :: 3.12
Classifier: Programming Language :: Python :: 3.13
Classifier: Operating System :: MacOS
Classifier: Operating System :: Microsoft :: Windows
Classifier: Operating System :: POSIX :: Linux
Requires-Python: >=3.11
License-File: LICENSE
Requires-Dist: agi-cluster
Requires-Dist: astor
Requires-Dist: fastparquet
Requires-Dist: geojson
Requires-Dist: humanize
Requires-Dist: jupyter-ai[all]
Requires-Dist: keras
Requires-Dist: matplotlib
Requires-Dist: mlflow
Requires-Dist: networkx
Requires-Dist: numba
Requires-Dist: openai
Requires-Dist: pathspec
Requires-Dist: plotly
Requires-Dist: polars
Requires-Dist: py7zr
Requires-Dist: seaborn
Requires-Dist: streamlit
Requires-Dist: streamlit-modal
Requires-Dist: streamlit_code_editor
Requires-Dist: streamlit_extras
Requires-Dist: tomli
Requires-Dist: ydata
Requires-Dist: tomli_w
Requires-Dist: asyncssh
Requires-Dist: watchdog
Dynamic: license-file
